{
    "Summary": [
        [
            "Date",
            "2024-09-02 17:16:03"
        ],
        [
            "User",
            "SPATIALNETWORX\\rakk0001"
        ],
        [
            "Request URL",
            "http://10.246.4.103/spatialSTORM/spatialSUITE/v8_6_2/custom/PayloadReport?ReportType=PIF&Sheath=&Segment="
        ],
        [
            "Request Processing time (s)",
            0.0040260999999999995
        ]
    ],
    "Issues": [
        {
            "Code": "009",
            "CodeMessage": "Data or input error: Could not identify exactly one resource matching the provided identifier",
            "Detail": "Could not match a Sheath to the name provided: ",
            "Severity": "ERROR",
            "StackTrace": [
                "   at CustomServicesPlugin.WorkOrderReports.PayloadReportHandlerBase.gather(IStore store) in c:\\jenkins\\TestPipelines\\Services\\5\\Shaw\\spatialstorm\\DEV\\CSharp\\CustomServicesPlugin\\WorkOrderReports\\PayloadReport.cs:line 156",
                "   at CustomServicesPlugin.WorkOrderReports.PayloadReportHandlerBase.Request(IStore store, Context context, PayloadReportRequest request) in c:\\jenkins\\TestPipelines\\Services\\5\\Shaw\\spatialstorm\\DEV\\CSharp\\CustomServicesPlugin\\WorkOrderReports\\PayloadReport.cs:line 72"
            ],
            "InnerException": null
        }
    ],
    "Data": null
}